django.py
django/__init__.py
infoip/__init__.py
infoip/django.py
infoip-0.1.8.dist-info/DESCRIPTION.rst
infoip-0.1.8.dist-info/METADATA
infoip-0.1.8.dist-info/RECORD
infoip-0.1.8.dist-info/WHEEL
infoip-0.1.8.dist-info/metadata.json
infoip-0.1.8.dist-info/top_level.txt
