Metadata-Version: 2.0
Name: infoip
Version: 0.1.8
Summary: Get visitor geoip information from the request.
Home-page: https://github.com/ciokan/infoip-geoip-python-integrations
Author: Romeo Mihalcea
Author-email: romeo.mihalcea@gmail.com
License: BSD
Platform: UNKNOWN
Classifier: Environment :: Web Environment
Classifier: Framework :: Django
Classifier: Intended Audience :: Developers
Classifier: Operating System :: OS Independent
Classifier: Development Status :: 5 - Production/Stable
Classifier: License :: OSI Approved :: BSD License
Classifier: Programming Language :: Python
Classifier: Programming Language :: Python :: 3.5
Classifier: Programming Language :: Python :: 3.6
Classifier: Topic :: Internet :: WWW/HTTP
Classifier: Topic :: Internet :: WWW/HTTP :: Dynamic Content
